pdf2docx/__init__.py
pdf2docx/converter.py
pdf2docx/main.py
pdf2docx/common/Block.py
pdf2docx/common/Collection.py
pdf2docx/common/Element.py
pdf2docx/common/__init__.py
pdf2docx/common/algorithm.py
pdf2docx/common/constants.py
pdf2docx/common/docx.py
pdf2docx/common/share.py
pdf2docx/font/Fonts.py
pdf2docx/font/__init__.py
pdf2docx/gui/App.py
pdf2docx/gui/MainFrame.py
pdf2docx/gui/__init__.py
pdf2docx/gui/icon.ico
pdf2docx/image/Image.py
pdf2docx/image/ImageBlock.py
pdf2docx/image/ImageSpan.py
pdf2docx/image/ImagesExtractor.py
pdf2docx/image/__init__.py
pdf2docx/layout/Blocks.py
pdf2docx/layout/Column.py
pdf2docx/layout/Layout.py
pdf2docx/layout/Section.py
pdf2docx/layout/Sections.py
pdf2docx/layout/__init__.py
pdf2docx/page/BasePage.py
pdf2docx/page/Page.py
pdf2docx/page/Pages.py
pdf2docx/page/RawPage.py
pdf2docx/page/RawPageFactory.py
pdf2docx/page/RawPageFitz.py
pdf2docx/page/__init__.py
pdf2docx/shape/Path.py
pdf2docx/shape/Paths.py
pdf2docx/shape/Shape.py
pdf2docx/shape/Shapes.py
pdf2docx/shape/__init__.py
pdf2docx/table/Border.py
pdf2docx/table/Cell.py
pdf2docx/table/Cells.py
pdf2docx/table/Row.py
pdf2docx/table/Rows.py
pdf2docx/table/TableBlock.py
pdf2docx/table/TableStructure.py
pdf2docx/table/TablesConstructor.py
pdf2docx/table/__init__.py
pdf2docx/text/Char.py
pdf2docx/text/Line.py
pdf2docx/text/Lines.py
pdf2docx/text/Spans.py
pdf2docx/text/TextBlock.py
pdf2docx/text/TextSpan.py
pdf2docx/text/__init__.py
pdf2docx-0.5.7.dist-info/LICENSE
pdf2docx-0.5.7.dist-info/METADATA
pdf2docx-0.5.7.dist-info/WHEEL
pdf2docx-0.5.7.dist-info/entry_points.txt
pdf2docx-0.5.7.dist-info/top_level.txt
pdf2docx-0.5.7.dist-info/RECORD
