Metadata-Version: 2.1
Name: pdf2docx
Version: 0.5.7
Summary: Open source Python library converting pdf to docx.
Author: Artifex
Author-email: support@artifex.com
License: GPL v3
Keywords: pdf-to-word,pdf-to-docx
Requires-Python: >=3.6
License-File: LICENSE
